jetbrains_plugin_server/__init__.py
jetbrains_plugin_server/config.py
jetbrains_plugin_server/plugin_catalog.py
jetbrains_plugin_server/plugin_model.py
jetbrains_plugin_server/py.typed
jetbrains_plugin_server/schemas.py
jetbrains_plugin_server/server.py
jetbrains_plugin_server/to_xml.py
jetbrains_plugin_server/model/__init__.py
jetbrains_plugin_server/model/data_listing.py
jetbrains_plugin_server/model/errors.py
jetbrains_plugin_server/model/packages.py
jetbrains_plugin_server/tools/__init__.py
jetbrains_plugin_server/tools/dl_data.py
jetbrains_plugin_server/tools/gen_json_cache.py
jetbrains_plugin_server-0.1.3.dist-info/licenses/LICENSE.md
jetbrains_plugin_server-0.1.3.dist-info/METADATA
jetbrains_plugin_server-0.1.3.dist-info/WHEEL
jetbrains_plugin_server-0.1.3.dist-info/top_level.txt
jetbrains_plugin_server-0.1.3.dist-info/RECORD
