Metadata-Version: 2.4
Name: jetbrains-plugin-server
Version: 0.1.3
Summary: A server to serve jetbrains plugins
Author-email: azro352 <35503478+azro352@users.noreply.github.com>
License-Expression: MIT
Project-URL: Homepage, https://github.com/azro352/jetbrains-plugin-server
Project-URL: Documentation, https://github.com/azro352/jetbrains-plugin-server/blob/master/README.md
Project-URL: Repository, https://github.com/azro352/jetbrains-plugin-server.git
Project-URL: Bug Tracker, https://github.com/azro352/jetbrains-plugin-server/issues
Classifier: Development Status :: 4 - Beta
Classifier: Framework :: FastAPI
Classifier: Intended Audience :: Developers
Classifier: Programming Language :: Python
Classifier: Programming Language :: Python :: 3.10
Classifier: Programming Language :: Python :: 3.11
Classifier: Programming Language :: Python :: 3.12
Classifier: Programming Language :: Python :: 3.13
Classifier: Typing :: Typed
Requires-Python: >=3.10
License-File: LICENSE.md
Requires-Dist: fastapi~=0.115.12
Requires-Dist: markdown~=3.8
Requires-Dist: parameterized~=0.9.0
Requires-Dist: pydantic~=2.11.3
Requires-Dist: pydantic-extra-types[semver]~=2.10.3
Requires-Dist: requests~=2.32.3
Requires-Dist: semver~=3.0.4
Requires-Dist: uvicorn
Provides-Extra: offline
Requires-Dist: fastapi_offline; extra == "offline"
Dynamic: license-file
